[
  {
    "transit_time_chart": {
      "pay": true,
      "drilldown": [{
        
      }]
    },
    "road_from": {
      "path": [
        [
          31.230349,
          121.47374
        ],
        [
          31.32358,
          121.480942
        ],
        [
          31.399626,
          121.496124
        ]
      ],
      "dist": 18.96733,
      "distance": 28.495,
      "transit_time_seconds": 2931,
      "transit_time_days": "0 days",
      "name": "Shanghai, China",
      "speed": "35 km/h",
      "lat": 31.230416,
      "lng": 121.473701
    },
    "sea": {
      "path": [
        [
          31.400090576935703,
          121.49711250347934
        ],
        [
          27.770922840395347,
          145.1390414279574
        ],
        [
          10.834806736540354,
          -104.5319569244781
        ],
        [
          7.205639,
          -80.89002800000003
        ],
        [
          7.210768099999999,
          -80.82246965000002
        ],
        [
          7.2347039,
          -80.50719735000001
        ],
        [
          7.239833,
          -80.439639
        ],
        [
          7.28132885,
          -80.37256395000003
        ],
        [
          7.47497615,
          -80.05954705000005
        ],
        [
          7.516472,
          -79.99247200000002
        ],
        [
          7.73054345,
          -79.92549055
        ],
        [
          8.729543549999999,
          -79.61291045000002
        ],
        [
          8.943615,
          -79.545929
        ],
        [
          9.0070242,
          -79.59980015000002
        ],
        [
          9.3029338,
          -79.85119885
        ],
        [
          9.366343,
          -79.90507000000002
        ],
        [
          10.99826245,
          -79.04075110000002
        ],
        [
          18.61388655,
          -75.0072629
        ],
        [
          20.245806,
          -74.142944
        ],
        [
          20.571743400000003,
          -73.97188160000002
        ],
        [
          22.092784599999998,
          -73.17359040000002
        ],
        [
          22.418722,
          -73.00252799999998
        ],
        [
          25.955034549999997,
          -71.02908630000002
        ],
        [
          42.45782644999999,
          -61.81969170000002
        ],
        [
          45.994139,
          -59.84625
        ],
        [
          46.279459849999995,
          -59.781150000000025
        ],
        [
          47.610957150000004,
          -59.47735
        ],
        [
          47.896278,
          -59.41224999999997
        ],
        [
          47.981823750000004,
          -59.390966649999996
        ],
        [
          48.38103725,
          -59.29164435000001
        ],
        [
          48.466583,
          -59.27036099999998
        ],
        [
          48.80196635,
          -58.99143600000002
        ],
        [
          50.36708865,
          -57.689786000000026
        ],
        [
          50.702472,
          -57.41086100000001
        ],
        [
          50.91035115,
          -57.15311105000001
        ],
        [
          51.880453849999995,
          -55.950277949999986
        ],
        [
          52.088333,
          -55.69252799999998
        ],
        [
          52.14182465,
          -55.682777999999985
        ],
        [
          52.391452349999994,
          -55.63727799999998
        ],
        [
          52.444944,
          -55.627527999999984
        ],
        [
          52.5784482,
          -55.65353214999999
        ],
        [
          53.201467799999996,
          -55.77488484999998
        ],
        [
          53.334972,
          -55.800888999999984
        ],
        [
          55.44872403913394,
          -56.528074705033816
        ],
        [
          65.31290022175902,
          -59.92160799519178
        ],
        [
          67.42665226089298,
          -60.64879370022561
        ],
        [
          68.77038671821255,
          -61.99435332558801
        ],
        [
          75.04114751903722,
          -68.27363157727928
        ],
        [
          76.3848819763568,
          -69.61919120264167
        ],
        [
          76.54714967990827,
          -69.55881252225043
        ],
        [
          77.3043989631485,
          -69.27704534709125
        ],
        [
          77.4666666667,
          -69.21666666670001
        ]
      ],
      "dist": 24820.465292,
      "transit_time_seconds": 3711318,
      "transit_time_days": "42 days",
      "from_name": "Shanghai",
      "to_name": "Qaanaaq",
      "speed": "13 knots",
      "from_lat": 31.400090576935703,
      "from_lng": 121.49711250347931,
      "to_lat": 77.4666666667,
      "to_lng": -69.2166666667
    },
    "road_to": {
      "path": [
        [
          77.4666666667,
          -69.2166666667
        ],
        [
          456.48226,
          30.7233095
        ]
      ],
      "distance": 1451.45544,
      "transit_time_seconds": 149293,
      "transit_time_days": "1 days",
      "name": "Alert, NU, Canada",
      "speed": "35 km/h",
      "lat": 456.48226,
      "lng": 30.7233095
    }
  }
]